{"is_source_file": true, "format": "Java", "description": "Defines the InvalidMoveException class, a custom runtime exception thrown when a chess move is invalid.", "external_files": [], "external_methods": [], "published": [], "classes": [{"name": "InvalidMoveException", "description": "A custom exception class indicating an illegal move in the chess game."}], "methods": [{"name": "InvalidMoveException", "description": "Constructor that creates an exception with the provided message."}], "calls": [], "search-terms": ["InvalidMoveException", "com.example.chessgamebackend.exception", "RuntimeException", "illegal move"], "state": 2, "file_id": 23, "knowledge_revision": 50, "git_revision": "", "hash": "40d4765714a4415f8cdc94cafb8de8bf", "format-version": 4, "code-base-name": "chess_game_backend", "filename": "chess_game_backend/src/main/java/com/example/chessgamebackend/exception/InvalidMoveException.java", "revision_history": [{"50": ""}]}